hpcflow/__init__.py
hpcflow/_version.py
hpcflow/api.py
hpcflow/base_db.py
hpcflow/cli.py
hpcflow/config.py
hpcflow/copytree.py
hpcflow/errors.py
hpcflow/init_db.py
hpcflow/models.py
hpcflow/nesting.py
hpcflow/profiles.py
hpcflow/project.py
hpcflow/scheduler.py
hpcflow/utils.py
hpcflow/validation.py
hpcflow/variables.py
hpcflow/archive/__init__.py
hpcflow/archive/archive.py
hpcflow/archive/errors.py
hpcflow/archive/cloud/__init__.py
hpcflow/archive/cloud/cloud.py
hpcflow/archive/cloud/errors.py
hpcflow/archive/cloud/providers/__init__.py
hpcflow/archive/cloud/providers/dropbox.py
hpcflow/data/examples/_config.yml
hpcflow/data/examples/thinking.yml
hpcflow/data/examples/damask/demo/1.run.yml
hpcflow/data/examples/damask/demo/2.process.yml
hpcflow/data/examples/damask/demo/geom.geom
hpcflow/data/examples/damask/demo/load.load
hpcflow/data/examples/damask/demo/material.config
hpcflow/data/examples/damask/inputs/geom.geom
hpcflow/data/examples/damask/inputs/load.load
hpcflow/data/examples/damask/inputs/material.config
hpcflow/data/examples/damask/profiles/_variable_lookup.yml
hpcflow/data/examples/damask/profiles/damask.yml
hpcflow/data/examples/damask/profiles/damask_process.yml
hpcflow/data/examples/damask/profiles/damask_run.yml
hpcflow/data/examples/damask/profiles/default.yml
hpcflow-0.1.16.dist-info/METADATA
hpcflow-0.1.16.dist-info/WHEEL
hpcflow-0.1.16.dist-info/entry_points.txt
hpcflow-0.1.16.dist-info/top_level.txt
hpcflow-0.1.16.dist-info/RECORD
