Metadata-Version: 2.1
Name: hpcflow
Version: 0.1.16
Summary: Generate and submit jobscripts for an automated simulate, process, archive workflow on high performance computing (HPC) systems.
Home-page: UNKNOWN
Author: Adam J. Plowman
Author-email: adam.plowman@manchester.ac.uk
License: UNKNOWN
Platform: UNKNOWN
Classifier: Development Status :: 3 - Alpha
Classifier: Intended Audience :: Science/Research
Classifier: Topic :: Scientific/Engineering
Classifier: Programming Language :: Python :: 3.6
Classifier: Programming Language :: Python :: 3.7
Classifier: Operating System :: POSIX
Requires-Dist: click (>7.0)
Requires-Dist: ruamel.yaml
Requires-Dist: sqlalchemy (>=1.4.0)
Requires-Dist: dropbox (==10.1.2)
Requires-Dist: six (>1.11.0)
Requires-Dist: beautifultable
